k9crypt/__init__.py
k9crypt/constants.py
k9crypt/k9crypt.py
k9crypt-0.1.0.dist-info/LICENSE
k9crypt-0.1.0.dist-info/METADATA
k9crypt-0.1.0.dist-info/WHEEL
k9crypt-0.1.0.dist-info/top_level.txt
k9crypt-0.1.0.dist-info/RECORD
